{
  "courseCode": "BIOKL",
  "aliases": [
    "BKL"
  ],
  "stats": [
    {
      "semesterName": "ZS 2024/2025 - LDF",
      "semesterId": "765",
      "year": 2024,
      "evaluationType": "exam",
      "sourceUrl": "https://is.mendelu.cz/auth/student/hodnoceni.pl?fakulta=38;obdobi=765;predmet=153478;lang=cz",
      "totalPass": 251,
      "totalFail": 2,
      "terms": [
        {
          "term": "Všechny termíny",
          "grades": {
            "A": 40,
            "B": 40,
            "C": 55,
            "D": 35,
            "E": 81,
            "F": 1,
            "FN": 1
          },
          "pass": 251,
          "fail": 2
        }
      ]
    },
    {
      "semesterName": "ZS 2023/2024 - ZF",
      "semesterId": "735",
      "year": 2023,
      "evaluationType": "exam",
      "sourceUrl": "https://is.mendelu.cz/auth/student/hodnoceni.pl?fakulta=60;obdobi=735;predmet=147942;lang=cz",
      "totalPass": 2,
      "totalFail": 0,
      "terms": [
        {
          "term": "Všechny termíny",
          "grades": {
            "A": 0,
            "B": 0,
            "C": 0,
            "D": 1,
            "E": 1,
            "F": 0,
            "FN": 0
          },
          "pass": 2,
          "fail": 0
        }
      ]
    },
    {
      "semesterName": "ZS 2023/2024 - AF",
      "semesterId": "733",
      "year": 2023,
      "evaluationType": "exam",
      "sourceUrl": "https://is.mendelu.cz/auth/student/hodnoceni.pl?fakulta=14;obdobi=733;predmet=146357;lang=cz",
      "totalPass": 33,
      "totalFail": 0,
      "terms": [
        {
          "term": "Všechny termíny",
          "grades": {
            "A": 8,
            "B": 7,
            "C": 10,
            "D": 5,
            "E": 3,
            "F": 0,
            "FN": 0
          },
          "pass": 33,
          "fail": 0
        }
      ]
    },
    {
      "semesterName": "ZS 2023/2024 - LDF",
      "semesterId": "732",
      "year": 2023,
      "evaluationType": "exam",
      "sourceUrl": "https://is.mendelu.cz/auth/student/hodnoceni.pl?fakulta=38;obdobi=732;predmet=147123;lang=cz",
      "totalPass": 196,
      "totalFail": 3,
      "terms": [
        {
          "term": "Všechny termíny",
          "grades": {
            "A": 36,
            "B": 29,
            "C": 43,
            "D": 34,
            "E": 54,
            "F": 3,
            "FN": 0
          },
          "pass": 196,
          "fail": 3
        }
      ]
    },
    {
      "semesterName": "ZS 2024/2025 - AF",
      "semesterId": "704",
      "year": 2024,
      "evaluationType": "exam",
      "sourceUrl": "https://is.mendelu.cz/auth/student/hodnoceni.pl?fakulta=14;obdobi=704;predmet=152585;lang=cz",
      "totalPass": 24,
      "totalFail": 0,
      "terms": [
        {
          "term": "Všechny termíny",
          "grades": {
            "A": 7,
            "B": 8,
            "C": 3,
            "D": 2,
            "E": 4,
            "F": 0,
            "FN": 0
          },
          "pass": 24,
          "fail": 0
        }
      ]
    },
    {
      "semesterName": "ZS 2022/2023 - AF",
      "semesterId": "696",
      "year": 2022,
      "evaluationType": "exam",
      "sourceUrl": "https://is.mendelu.cz/auth/student/hodnoceni.pl?fakulta=14;obdobi=696;predmet=136694;lang=cz",
      "totalPass": 36,
      "totalFail": 0,
      "terms": [
        {
          "term": "Všechny termíny",
          "grades": {
            "A": 12,
            "B": 8,
            "C": 8,
            "D": 5,
            "E": 3,
            "F": 0,
            "FN": 0
          },
          "pass": 36,
          "fail": 0
        }
      ]
    },
    {
      "semesterName": "ZS 2022/2023 - LDF",
      "semesterId": "690",
      "year": 2022,
      "evaluationType": "exam",
      "sourceUrl": "https://is.mendelu.cz/auth/student/hodnoceni.pl?fakulta=38;obdobi=690;predmet=137723;lang=cz",
      "totalPass": 212,
      "totalFail": 2,
      "terms": [
        {
          "term": "Všechny termíny",
          "grades": {
            "A": 40,
            "B": 32,
            "C": 48,
            "D": 41,
            "E": 51,
            "F": 2,
            "FN": 0
          },
          "pass": 212,
          "fail": 2
        }
      ]
    },
    {
      "semesterName": "LS 2021/2022 - ZF",
      "semesterId": "683",
      "year": 2021,
      "evaluationType": "exam",
      "sourceUrl": "https://is.mendelu.cz/auth/student/hodnoceni.pl?fakulta=60;obdobi=683;predmet=133996;lang=cz",
      "totalPass": 53,
      "totalFail": 23,
      "terms": [
        {
          "term": "Všechny termíny",
          "grades": {
            "A": 3,
            "B": 11,
            "C": 8,
            "D": 17,
            "E": 14,
            "F": 17,
            "FN": 6
          },
          "pass": 53,
          "fail": 23
        }
      ]
    },
    {
      "semesterName": "LS 2021/2022 - LDF",
      "semesterId": "673",
      "year": 2021,
      "evaluationType": "exam",
      "sourceUrl": "https://is.mendelu.cz/auth/student/hodnoceni.pl?fakulta=38;obdobi=673;predmet=135658;lang=cz",
      "totalPass": 4,
      "totalFail": 0,
      "terms": [
        {
          "term": "Všechny termíny",
          "grades": {
            "A": 0,
            "B": 0,
            "C": 1,
            "D": 1,
            "E": 2,
            "F": 0,
            "FN": 0
          },
          "pass": 4,
          "fail": 0
        }
      ]
    },
    {
      "semesterName": "ZS 2021/2022 - AF",
      "semesterId": "651",
      "year": 2021,
      "evaluationType": "exam",
      "sourceUrl": "https://is.mendelu.cz/auth/student/hodnoceni.pl?fakulta=14;obdobi=651;predmet=129823;lang=cz",
      "totalPass": 33,
      "totalFail": 0,
      "terms": [
        {
          "term": "Všechny termíny",
          "grades": {
            "A": 6,
            "B": 6,
            "C": 12,
            "D": 6,
            "E": 3,
            "F": 0,
            "FN": 0
          },
          "pass": 33,
          "fail": 0
        }
      ]
    },
    {
      "semesterName": "ZS 2021/2022 - LDF",
      "semesterId": "649",
      "year": 2021,
      "evaluationType": "exam",
      "sourceUrl": "https://is.mendelu.cz/auth/student/hodnoceni.pl?fakulta=38;obdobi=649;predmet=129975;lang=cz",
      "totalPass": 163,
      "totalFail": 3,
      "terms": [
        {
          "term": "Všechny termíny",
          "grades": {
            "A": 32,
            "B": 31,
            "C": 40,
            "D": 21,
            "E": 39,
            "F": 2,
            "FN": 1
          },
          "pass": 163,
          "fail": 3
        }
      ]
    },
    {
      "semesterName": "LS 2020/2021 - AF",
      "semesterId": "640",
      "year": 2020,
      "evaluationType": "exam",
      "sourceUrl": "https://is.mendelu.cz/auth/student/hodnoceni.pl?fakulta=14;obdobi=640;predmet=126354;lang=cz",
      "totalPass": 10,
      "totalFail": 0,
      "terms": [
        {
          "term": "Všechny termíny",
          "grades": {
            "A": 7,
            "B": 0,
            "C": 1,
            "D": 2,
            "E": 0,
            "F": 0,
            "FN": 0
          },
          "pass": 10,
          "fail": 0
        }
      ]
    },
    {
      "semesterName": "LS 2020/2021 - ZF",
      "semesterId": "638",
      "year": 2020,
      "evaluationType": "exam",
      "sourceUrl": "https://is.mendelu.cz/auth/student/hodnoceni.pl?fakulta=60;obdobi=638;predmet=126773;lang=cz",
      "totalPass": 77,
      "totalFail": 4,
      "terms": [
        {
          "term": "Všechny termíny",
          "grades": {
            "A": 3,
            "B": 4,
            "C": 18,
            "D": 21,
            "E": 31,
            "F": 4,
            "FN": 0
          },
          "pass": 77,
          "fail": 4
        }
      ]
    },
    {
      "semesterName": "ZS 2020/2021 - LDF",
      "semesterId": "588",
      "year": 2020,
      "evaluationType": "exam",
      "sourceUrl": "https://is.mendelu.cz/auth/student/hodnoceni.pl?fakulta=38;obdobi=588;predmet=124286;lang=cz",
      "totalPass": 157,
      "totalFail": 0,
      "terms": [
        {
          "term": "Všechny termíny",
          "grades": {
            "A": 34,
            "B": 25,
            "C": 37,
            "D": 32,
            "E": 29,
            "F": 0,
            "FN": 0
          },
          "pass": 157,
          "fail": 0
        }
      ]
    },
    {
      "semesterName": "LS 2019/2020 - ZF",
      "semesterId": "580",
      "year": 2019,
      "evaluationType": "exam",
      "sourceUrl": "https://is.mendelu.cz/auth/student/hodnoceni.pl?fakulta=60;obdobi=580;predmet=120080;lang=cz",
      "totalPass": 79,
      "totalFail": 4,
      "terms": [
        {
          "term": "Všechny termíny",
          "grades": {
            "A": 1,
            "B": 3,
            "C": 12,
            "D": 29,
            "E": 34,
            "F": 4,
            "FN": 0
          },
          "pass": 79,
          "fail": 4
        }
      ]
    }
  ],
  "lastUpdated": "2026-01-12T08:53:23.064446Z"
}