{
  "courseCode": "CV1",
  "aliases": [],
  "stats": [
    {
      "semesterName": "ZS 2024/2025 - LDF",
      "semesterId": "765",
      "year": 2024,
      "evaluationType": "credit",
      "sourceUrl": "https://is.mendelu.cz/auth/student/hodnoceni.pl?fakulta=38;obdobi=765;predmet=153321;lang=cz",
      "totalPass": 55,
      "totalFail": 2,
      "terms": [
        {
          "term": "Všechny termíny",
          "grades": {
            "zap": 55,
            "nezap": 2,
            "zap-nedost": 0
          },
          "pass": 55,
          "fail": 2
        }
      ]
    },
    {
      "semesterName": "ZS 2023/2024 - LDF",
      "semesterId": "732",
      "year": 2023,
      "evaluationType": "credit",
      "sourceUrl": "https://is.mendelu.cz/auth/student/hodnoceni.pl?fakulta=38;obdobi=732;predmet=146968;lang=cz",
      "totalPass": 56,
      "totalFail": 4,
      "terms": [
        {
          "term": "Všechny termíny",
          "grades": {
            "zap": 56,
            "nezap": 4,
            "zap-nedost": 0
          },
          "pass": 56,
          "fail": 4
        }
      ]
    },
    {
      "semesterName": "ZS 2022/2023 - LDF",
      "semesterId": "690",
      "year": 2022,
      "evaluationType": "credit",
      "sourceUrl": "https://is.mendelu.cz/auth/student/hodnoceni.pl?fakulta=38;obdobi=690;predmet=137762;lang=cz",
      "totalPass": 51,
      "totalFail": 2,
      "terms": [
        {
          "term": "Všechny termíny",
          "grades": {
            "zap": 51,
            "nezap": 2,
            "zap-nedost": 0
          },
          "pass": 51,
          "fail": 2
        }
      ]
    },
    {
      "semesterName": "ZS 2021/2022 - LDF",
      "semesterId": "649",
      "year": 2021,
      "evaluationType": "credit",
      "sourceUrl": "https://is.mendelu.cz/auth/student/hodnoceni.pl?fakulta=38;obdobi=649;predmet=130005;lang=cz",
      "totalPass": 47,
      "totalFail": 2,
      "terms": [
        {
          "term": "Všechny termíny",
          "grades": {
            "zap": 47,
            "nezap": 2,
            "zap-nedost": 0
          },
          "pass": 47,
          "fail": 2
        }
      ]
    },
    {
      "semesterName": "ZS 2020/2021 - LDF",
      "semesterId": "588",
      "year": 2020,
      "evaluationType": "credit",
      "sourceUrl": "https://is.mendelu.cz/auth/student/hodnoceni.pl?fakulta=38;obdobi=588;predmet=123873;lang=cz",
      "totalPass": 53,
      "totalFail": 1,
      "terms": [
        {
          "term": "Všechny termíny",
          "grades": {
            "zap": 53,
            "nezap": 0,
            "zap-nedost": 1
          },
          "pass": 53,
          "fail": 1
        }
      ]
    }
  ],
  "lastUpdated": "2026-01-12T08:53:23.064446Z"
}