{
  "courseCode": "EBA-EKTU",
  "aliases": [],
  "stats": [
    {
      "semesterName": "ZS 2024/2025 - PEF",
      "semesterId": "754",
      "year": 2024,
      "evaluationType": "exam",
      "sourceUrl": "https://is.mendelu.cz/auth/student/hodnoceni.pl?fakulta=2;obdobi=754;predmet=152029;lang=cz",
      "totalPass": 14,
      "totalFail": 2,
      "terms": [
        {
          "term": "Všechny termíny",
          "grades": {
            "A": 0,
            "B": 1,
            "C": 3,
            "D": 5,
            "E": 5,
            "F": 2,
            "FN": 0
          },
          "pass": 14,
          "fail": 2
        }
      ]
    },
    {
      "semesterName": "ZS 2023/2024 - PEF",
      "semesterId": "734",
      "year": 2023,
      "evaluationType": "exam",
      "sourceUrl": "https://is.mendelu.cz/auth/student/hodnoceni.pl?fakulta=2;obdobi=734;predmet=142549;lang=cz",
      "totalPass": 14,
      "totalFail": 4,
      "terms": [
        {
          "term": "Všechny termíny",
          "grades": {
            "A": 0,
            "B": 0,
            "C": 2,
            "D": 6,
            "E": 6,
            "F": 4,
            "FN": 0
          },
          "pass": 14,
          "fail": 4
        }
      ]
    },
    {
      "semesterName": "ZS 2022/2023 - PEF",
      "semesterId": "689",
      "year": 2022,
      "evaluationType": "exam",
      "sourceUrl": "https://is.mendelu.cz/auth/student/hodnoceni.pl?fakulta=2;obdobi=689;predmet=134895;lang=cz",
      "totalPass": 8,
      "totalFail": 11,
      "terms": [
        {
          "term": "Všechny termíny",
          "grades": {
            "A": 0,
            "B": 0,
            "C": 1,
            "D": 2,
            "E": 5,
            "F": 6,
            "FN": 5
          },
          "pass": 8,
          "fail": 11
        }
      ]
    },
    {
      "semesterName": "ZS 2021/2022 - PEF",
      "semesterId": "650",
      "year": 2021,
      "evaluationType": "exam",
      "sourceUrl": "https://is.mendelu.cz/auth/student/hodnoceni.pl?fakulta=2;obdobi=650;predmet=128335;lang=cz",
      "totalPass": 7,
      "totalFail": 6,
      "terms": [
        {
          "term": "Všechny termíny",
          "grades": {
            "A": 0,
            "B": 0,
            "C": 0,
            "D": 1,
            "E": 6,
            "F": 4,
            "FN": 2
          },
          "pass": 7,
          "fail": 6
        }
      ]
    }
  ],
  "lastUpdated": "2026-01-12T08:53:23.064446Z"
}