{
  "courseCode": "EBC-POL",
  "stats": [
    {
      "semesterName": "ZS 2022/2023 - PEF",
      "semesterId": "689",
      "year": 2022,
      "sourceUrl": "https://is.mendelu.cz/auth/student/hodnoceni.pl?fakulta=2;obdobi=689;predmet=137218;lang=cz",
      "totalPass": 34,
      "totalFail": 0,
      "terms": [
        {
          "term": "Všechny termíny",
          "grades": {
            "A": 2,
            "B": 7,
            "C": 12,
            "D": 10,
            "E": 3,
            "F": 0,
            "FN": 0
          },
          "pass": 34,
          "fail": 0
        }
      ]
    },
    {
      "semesterName": "ZS 2021/2022 - PEF",
      "semesterId": "650",
      "year": 2021,
      "sourceUrl": "https://is.mendelu.cz/auth/student/hodnoceni.pl?fakulta=2;obdobi=650;predmet=130648;lang=cz",
      "totalPass": 19,
      "totalFail": 0,
      "terms": [
        {
          "term": "Všechny termíny",
          "grades": {
            "A": 4,
            "B": 5,
            "C": 4,
            "D": 3,
            "E": 3,
            "F": 0,
            "FN": 0
          },
          "pass": 19,
          "fail": 0
        }
      ]
    }
  ],
  "lastUpdated": "2026-01-12T09:33:38.910Z"
}