{
  "courseCode": "EBC-DS",
  "stats": [
    {
      "semesterName": "ZS 2024/2025 - PEF",
      "semesterId": "754",
      "year": 2024,
      "sourceUrl": "https://is.mendelu.cz/auth/student/hodnoceni.pl?fakulta=2;obdobi=754;predmet=152539;lang=cz",
      "totalPass": 308,
      "totalFail": 75,
      "terms": [
        {
          "term": "Všechny termíny",
          "grades": {
            "A": 33,
            "B": 36,
            "C": 68,
            "D": 68,
            "E": 103,
            "F": 24,
            "FN": 51
          },
          "pass": 308,
          "fail": 75
        }
      ]
    },
    {
      "semesterName": "ZS 2023/2024 - PEF",
      "semesterId": "734",
      "year": 2023,
      "sourceUrl": "https://is.mendelu.cz/auth/student/hodnoceni.pl?fakulta=2;obdobi=734;predmet=142411;lang=cz",
      "totalPass": 292,
      "totalFail": 85,
      "terms": [
        {
          "term": "Všechny termíny",
          "grades": {
            "A": 16,
            "B": 25,
            "C": 49,
            "D": 84,
            "E": 118,
            "F": 38,
            "FN": 47
          },
          "pass": 292,
          "fail": 85
        }
      ]
    },
    {
      "semesterName": "ZS 2022/2023 - PEF",
      "semesterId": "689",
      "year": 2022,
      "sourceUrl": "https://is.mendelu.cz/auth/student/hodnoceni.pl?fakulta=2;obdobi=689;predmet=134817;lang=cz",
      "totalPass": 298,
      "totalFail": 92,
      "terms": [
        {
          "term": "Všechny termíny",
          "grades": {
            "A": 9,
            "B": 38,
            "C": 52,
            "D": 84,
            "E": 115,
            "F": 14,
            "FN": 78
          },
          "pass": 298,
          "fail": 92
        }
      ]
    },
    {
      "semesterName": "ZS 2021/2022 - PEF",
      "semesterId": "650",
      "year": 2021,
      "sourceUrl": "https://is.mendelu.cz/auth/student/hodnoceni.pl?fakulta=2;obdobi=650;predmet=127146;lang=cz",
      "totalPass": 229,
      "totalFail": 86,
      "terms": [
        {
          "term": "Všechny termíny",
          "grades": {
            "A": 7,
            "B": 20,
            "C": 47,
            "D": 73,
            "E": 82,
            "F": 5,
            "FN": 81
          },
          "pass": 229,
          "fail": 86
        }
      ]
    },
    {
      "semesterName": "ZS 2020/2021 - PEF",
      "semesterId": "584",
      "year": 2020,
      "sourceUrl": "https://is.mendelu.cz/auth/student/hodnoceni.pl?fakulta=2;obdobi=584;predmet=120472;lang=cz",
      "totalPass": 218,
      "totalFail": 121,
      "terms": [
        {
          "term": "Všechny termíny",
          "grades": {
            "A": 4,
            "B": 10,
            "C": 36,
            "D": 55,
            "E": 113,
            "F": 19,
            "FN": 102
          },
          "pass": 218,
          "fail": 121
        }
      ]
    }
  ],
  "lastUpdated": "2026-01-12T09:33:38.882Z"
}