{
  "courseCode": "ENC-UFI",
  "stats": [
    {
      "semesterName": "ZS 2022/2023 - PEF",
      "semesterId": "689",
      "year": 2022,
      "totalPass": 46,
      "totalFail": 13,
      "terms": [
        {
          "term": "termín 1",
          "grades": {
            "A": 16,
            "B": 11,
            "C": 7,
            "D": 3,
            "E": 3,
            "F": 8,
            "FN": 3
          },
          "pass": 40,
          "fail": 11
        },
        {
          "term": "termín 2",
          "grades": {
            "A": 1,
            "B": 0,
            "C": 1,
            "D": 0,
            "E": 3,
            "F": 2,
            "FN": 0
          },
          "pass": 5,
          "fail": 2
        },
        {
          "term": "termín 3",
          "grades": {
            "A": 0,
            "B": 0,
            "C": 0,
            "D": 0,
            "E": 1,
            "F": 0,
            "FN": 0
          },
          "pass": 1,
          "fail": 0
        }
      ]
    },
    {
      "semesterName": "ZS 2023/2024 - PEF",
      "semesterId": "734",
      "year": 2023,
      "sourceUrl": "https://is.mendelu.cz/auth/student/hodnoceni.pl?fakulta=2;obdobi=734;predmet=143620;lang=cz",
      "totalPass": 35,
      "totalFail": 3,
      "terms": [
        {
          "term": "Všechny termíny",
          "grades": {
            "A": 8,
            "B": 5,
            "C": 7,
            "D": 11,
            "E": 4,
            "F": 2,
            "FN": 1
          },
          "pass": 35,
          "fail": 3
        }
      ]
    },
    {
      "semesterName": "ZS 2024/2025 - PEF",
      "semesterId": "754",
      "year": 2024,
      "sourceUrl": "https://is.mendelu.cz/auth/student/hodnoceni.pl?fakulta=2;obdobi=754;predmet=153221;lang=cz",
      "totalPass": 21,
      "totalFail": 0,
      "terms": [
        {
          "term": "Všechny termíny",
          "grades": {
            "A": 6,
            "B": 5,
            "C": 4,
            "D": 1,
            "E": 5,
            "F": 0,
            "FN": 0
          },
          "pass": 21,
          "fail": 0
        }
      ]
    }
  ],
  "lastUpdated": "2025-12-23T12:35:07.444Z"
}