{
  "courseCode": "KZ2",
  "aliases": [],
  "stats": [
    {
      "semesterName": "LS 2021/2022 - ZF",
      "semesterId": "683",
      "year": 2021,
      "type": "exam",
      "sourceUrl": "https://is.mendelu.cz/auth/student/hodnoceni.pl?fakulta=60;obdobi=683;predmet=134047;lang=cz",
      "totalPass": 4,
      "totalFail": 0,
      "terms": [
        {
          "term": "Všechny termíny",
          "grades": {
            "A": 2,
            "B": 1,
            "C": 0,
            "D": 1,
            "E": 0,
            "F": 0,
            "FN": 0
          },
          "pass": 4,
          "fail": 0
        }
      ]
    },
    {
      "semesterName": "LS 2020/2021 - ZF",
      "semesterId": "638",
      "year": 2020,
      "type": "exam",
      "sourceUrl": "https://is.mendelu.cz/auth/student/hodnoceni.pl?fakulta=60;obdobi=638;predmet=126739;lang=cz",
      "totalPass": 70,
      "totalFail": 0,
      "terms": [
        {
          "term": "Všechny termíny",
          "grades": {
            "A": 8,
            "B": 13,
            "C": 15,
            "D": 14,
            "E": 20,
            "F": 0,
            "FN": 0
          },
          "pass": 70,
          "fail": 0
        }
      ]
    },
    {
      "semesterName": "LS 2019/2020 - ZF",
      "semesterId": "580",
      "year": 2019,
      "type": "exam",
      "sourceUrl": "https://is.mendelu.cz/auth/student/hodnoceni.pl?fakulta=60;obdobi=580;predmet=120229;lang=cz",
      "totalPass": 47,
      "totalFail": 7,
      "terms": [
        {
          "term": "Všechny termíny",
          "grades": {
            "A": 6,
            "B": 5,
            "C": 18,
            "D": 11,
            "E": 7,
            "F": 6,
            "FN": 1
          },
          "pass": 47,
          "fail": 7
        }
      ]
    }
  ],
  "lastUpdated": "2026-01-16T05:55:31.283498Z"
}