{
  "courseCode": "LZE",
  "stats": [
    {
      "semesterName": "ZS 2024/2025 - LDF",
      "semesterId": "765",
      "year": 2024,
      "sourceUrl": "https://is.mendelu.cz/auth/student/hodnoceni.pl?fakulta=38;obdobi=765;predmet=153490;lang=cz",
      "totalPass": 205,
      "totalFail": 10,
      "terms": [
        {
          "term": "Všechny termíny",
          "grades": {
            "A": 5,
            "B": 26,
            "C": 60,
            "D": 48,
            "E": 66,
            "F": 4,
            "FN": 6
          },
          "pass": 205,
          "fail": 10
        }
      ]
    },
    {
      "semesterName": "ZS 2023/2024 - LDF",
      "semesterId": "732",
      "year": 2023,
      "sourceUrl": "https://is.mendelu.cz/auth/student/hodnoceni.pl?fakulta=38;obdobi=732;predmet=147262;lang=cz",
      "totalPass": 166,
      "totalFail": 13,
      "terms": [
        {
          "term": "Všechny termíny",
          "grades": {
            "A": 3,
            "B": 7,
            "C": 35,
            "D": 62,
            "E": 59,
            "F": 5,
            "FN": 8
          },
          "pass": 166,
          "fail": 13
        }
      ]
    },
    {
      "semesterName": "LS 2022/2023 - LDF",
      "semesterId": "725",
      "year": 2022,
      "sourceUrl": "https://is.mendelu.cz/auth/student/hodnoceni.pl?fakulta=38;obdobi=725;predmet=143119;lang=cz",
      "totalPass": 2,
      "totalFail": 0,
      "terms": [
        {
          "term": "Všechny termíny",
          "grades": {
            "A": 0,
            "B": 0,
            "C": 0,
            "D": 0,
            "E": 2,
            "F": 0,
            "FN": 0
          },
          "pass": 2,
          "fail": 0
        }
      ]
    },
    {
      "semesterName": "ZS 2022/2023 - LDF",
      "semesterId": "690",
      "year": 2022,
      "sourceUrl": "https://is.mendelu.cz/auth/student/hodnoceni.pl?fakulta=38;obdobi=690;predmet=136465;lang=cz",
      "totalPass": 174,
      "totalFail": 6,
      "terms": [
        {
          "term": "Všechny termíny",
          "grades": {
            "A": 0,
            "B": 11,
            "C": 39,
            "D": 55,
            "E": 69,
            "F": 4,
            "FN": 2
          },
          "pass": 174,
          "fail": 6
        }
      ]
    },
    {
      "semesterName": "ZS 2021/2022 - LDF",
      "semesterId": "649",
      "year": 2021,
      "sourceUrl": "https://is.mendelu.cz/auth/student/hodnoceni.pl?fakulta=38;obdobi=649;predmet=130014;lang=cz",
      "totalPass": 141,
      "totalFail": 3,
      "terms": [
        {
          "term": "Všechny termíny",
          "grades": {
            "A": 5,
            "B": 22,
            "C": 40,
            "D": 37,
            "E": 37,
            "F": 1,
            "FN": 2
          },
          "pass": 141,
          "fail": 3
        }
      ]
    },
    {
      "semesterName": "ZS 2020/2021 - LDF",
      "semesterId": "588",
      "year": 2020,
      "sourceUrl": "https://is.mendelu.cz/auth/student/hodnoceni.pl?fakulta=38;obdobi=588;predmet=123381;lang=cz",
      "totalPass": 132,
      "totalFail": 9,
      "terms": [
        {
          "term": "Všechny termíny",
          "grades": {
            "A": 2,
            "B": 19,
            "C": 25,
            "D": 45,
            "E": 41,
            "F": 4,
            "FN": 5
          },
          "pass": 132,
          "fail": 9
        }
      ]
    }
  ],
  "lastUpdated": "2026-01-12T09:33:39.514Z"
}