{
  "courseCode": "MMAZM",
  "aliases": [],
  "stats": [
    {
      "semesterName": "LS 2024/2025 - AF",
      "semesterId": "779",
      "year": 2024,
      "type": "exam",
      "sourceUrl": "https://is.mendelu.cz/auth/student/hodnoceni.pl?fakulta=14;obdobi=779;predmet=158125;lang=cz",
      "totalPass": 2,
      "totalFail": 0,
      "terms": [
        {
          "term": "Všechny termíny",
          "grades": {
            "A": 0,
            "B": 1,
            "C": 0,
            "D": 1,
            "E": 0,
            "F": 0,
            "FN": 0
          },
          "pass": 2,
          "fail": 0
        }
      ]
    },
    {
      "semesterName": "ZS 2023/2024 - AF",
      "semesterId": "733",
      "year": 2023,
      "type": "exam",
      "sourceUrl": "https://is.mendelu.cz/auth/student/hodnoceni.pl?fakulta=14;obdobi=733;predmet=147139;lang=cz",
      "totalPass": 27,
      "totalFail": 0,
      "terms": [
        {
          "term": "Všechny termíny",
          "grades": {
            "A": 8,
            "B": 6,
            "C": 8,
            "D": 4,
            "E": 1,
            "F": 0,
            "FN": 0
          },
          "pass": 27,
          "fail": 0
        }
      ]
    },
    {
      "semesterName": "ZS 2024/2025 - AF",
      "semesterId": "704",
      "year": 2024,
      "type": "exam",
      "sourceUrl": "https://is.mendelu.cz/auth/student/hodnoceni.pl?fakulta=14;obdobi=704;predmet=153731;lang=cz",
      "totalPass": 30,
      "totalFail": 2,
      "terms": [
        {
          "term": "Všechny termíny",
          "grades": {
            "A": 4,
            "B": 8,
            "C": 13,
            "D": 4,
            "E": 1,
            "F": 2,
            "FN": 0
          },
          "pass": 30,
          "fail": 2
        }
      ]
    },
    {
      "semesterName": "ZS 2022/2023 - AF",
      "semesterId": "696",
      "year": 2022,
      "type": "exam",
      "sourceUrl": "https://is.mendelu.cz/auth/student/hodnoceni.pl?fakulta=14;obdobi=696;predmet=137078;lang=cz",
      "totalPass": 44,
      "totalFail": 0,
      "terms": [
        {
          "term": "Všechny termíny",
          "grades": {
            "A": 8,
            "B": 11,
            "C": 14,
            "D": 7,
            "E": 4,
            "F": 0,
            "FN": 0
          },
          "pass": 44,
          "fail": 0
        }
      ]
    },
    {
      "semesterName": "ZS 2021/2022 - AF",
      "semesterId": "651",
      "year": 2021,
      "type": "exam",
      "sourceUrl": "https://is.mendelu.cz/auth/student/hodnoceni.pl?fakulta=14;obdobi=651;predmet=129799;lang=cz",
      "totalPass": 43,
      "totalFail": 2,
      "terms": [
        {
          "term": "Všechny termíny",
          "grades": {
            "A": 16,
            "B": 10,
            "C": 11,
            "D": 5,
            "E": 1,
            "F": 2,
            "FN": 0
          },
          "pass": 43,
          "fail": 2
        }
      ]
    }
  ],
  "lastUpdated": "2026-01-16T05:55:31.283498Z"
}