{
  "courseCode": "OTAJAT",
  "stats": [
    {
      "semesterName": "LS 2022/2023 - AF",
      "semesterId": "727",
      "year": 2022,
      "sourceUrl": "https://is.mendelu.cz/auth/student/hodnoceni.pl?fakulta=14;obdobi=727;predmet=141628;lang=cz",
      "totalPass": 33,
      "totalFail": 0,
      "terms": [
        {
          "term": "Všechny termíny",
          "grades": {
            "A": 9,
            "B": 7,
            "C": 7,
            "D": 6,
            "E": 4,
            "F": 0,
            "FN": 0
          },
          "pass": 33,
          "fail": 0
        }
      ]
    },
    {
      "semesterName": "LS 2023/2024 - AF",
      "semesterId": "752",
      "year": 2023,
      "sourceUrl": "https://is.mendelu.cz/auth/student/hodnoceni.pl?fakulta=14;obdobi=752;predmet=150692;lang=cz",
      "totalPass": 37,
      "totalFail": 0,
      "terms": [
        {
          "term": "Všechny termíny",
          "grades": {
            "A": 11,
            "B": 9,
            "C": 5,
            "D": 5,
            "E": 7,
            "F": 0,
            "FN": 0
          },
          "pass": 37,
          "fail": 0
        }
      ]
    },
    {
      "semesterName": "LS 2024/2025 - AF",
      "semesterId": "779",
      "year": 2024,
      "sourceUrl": "https://is.mendelu.cz/auth/student/hodnoceni.pl?fakulta=14;obdobi=779;predmet=157128;lang=cz",
      "totalPass": 41,
      "totalFail": 0,
      "terms": [
        {
          "term": "Všechny termíny",
          "grades": {
            "A": 10,
            "B": 8,
            "C": 15,
            "D": 3,
            "E": 5,
            "F": 0,
            "FN": 0
          },
          "pass": 41,
          "fail": 0
        }
      ]
    }
  ],
  "lastUpdated": "2025-12-23T12:35:07.575Z"
}