{
  "courseCode": "PRA22LS",
  "aliases": [],
  "stats": [
    {
      "semesterName": "ZS 2023/2024 - ZF",
      "semesterId": "735",
      "year": 2023,
      "evaluationType": "credit",
      "sourceUrl": "https://is.mendelu.cz/auth/student/hodnoceni.pl?fakulta=60;obdobi=735;predmet=148852;lang=cz",
      "totalPass": 2,
      "totalFail": 0,
      "terms": [
        {
          "term": "Všechny termíny",
          "grades": {
            "zap": 2,
            "nezap": 0,
            "zap-nedost": 0
          },
          "pass": 2,
          "fail": 0
        }
      ]
    },
    {
      "semesterName": "ZS 2022/2023 - ZF",
      "semesterId": "693",
      "year": 2022,
      "evaluationType": "credit",
      "sourceUrl": "https://is.mendelu.cz/auth/student/hodnoceni.pl?fakulta=60;obdobi=693;predmet=137000;lang=cz",
      "totalPass": 18,
      "totalFail": 0,
      "terms": [
        {
          "term": "Všechny termíny",
          "grades": {
            "zap": 18,
            "nezap": 0,
            "zap-nedost": 0
          },
          "pass": 18,
          "fail": 0
        }
      ]
    },
    {
      "semesterName": "LS 2021/2022 - ZF",
      "semesterId": "683",
      "year": 2021,
      "evaluationType": "credit",
      "sourceUrl": "https://is.mendelu.cz/auth/student/hodnoceni.pl?fakulta=60;obdobi=683;predmet=134037;lang=cz",
      "totalPass": 264,
      "totalFail": 6,
      "terms": [
        {
          "term": "Všechny termíny",
          "grades": {
            "zap": 264,
            "nezap": 6,
            "zap-nedost": 0
          },
          "pass": 264,
          "fail": 6
        }
      ]
    }
  ],
  "lastUpdated": "2026-01-12T08:53:23.064446Z"
}