{
  "courseCode": "SDR",
  "stats": [
    {
      "semesterName": "ZS 2020/2021 - LDF",
      "semesterId": "588",
      "year": 2020,
      "sourceUrl": "https://is.mendelu.cz/auth/student/hodnoceni.pl?fakulta=38;obdobi=588;predmet=123967;lang=cz",
      "totalPass": 31,
      "totalFail": 13,
      "terms": [
        {
          "term": "Všechny termíny",
          "grades": {
            "A": 2,
            "B": 3,
            "C": 10,
            "D": 7,
            "E": 9,
            "F": 12,
            "FN": 1
          },
          "pass": 31,
          "fail": 13
        }
      ]
    }
  ],
  "lastUpdated": "2026-01-12T09:33:40.202Z"
}