{
  "courseCode": "TTI1",
  "aliases": [],
  "stats": [
    {
      "semesterName": "ZS 2024/2025 - LDF",
      "semesterId": "765",
      "year": 2024,
      "evaluationType": "credit",
      "sourceUrl": "https://is.mendelu.cz/auth/student/hodnoceni.pl?fakulta=38;obdobi=765;predmet=153357;lang=cz",
      "totalPass": 28,
      "totalFail": 1,
      "terms": [
        {
          "term": "Všechny termíny",
          "grades": {
            "zap": 28,
            "nezap": 1,
            "zap-nedost": 0
          },
          "pass": 28,
          "fail": 1
        }
      ]
    },
    {
      "semesterName": "ZS 2023/2024 - LDF",
      "semesterId": "732",
      "year": 2023,
      "evaluationType": "credit",
      "sourceUrl": "https://is.mendelu.cz/auth/student/hodnoceni.pl?fakulta=38;obdobi=732;predmet=147001;lang=cz",
      "totalPass": 27,
      "totalFail": 3,
      "terms": [
        {
          "term": "Všechny termíny",
          "grades": {
            "zap": 27,
            "nezap": 0,
            "zap-nedost": 3
          },
          "pass": 27,
          "fail": 3
        }
      ]
    },
    {
      "semesterName": "ZS 2022/2023 - LDF",
      "semesterId": "690",
      "year": 2022,
      "evaluationType": "credit",
      "sourceUrl": "https://is.mendelu.cz/auth/student/hodnoceni.pl?fakulta=38;obdobi=690;predmet=137788;lang=cz",
      "totalPass": 25,
      "totalFail": 1,
      "terms": [
        {
          "term": "Všechny termíny",
          "grades": {
            "zap": 25,
            "nezap": 0,
            "zap-nedost": 1
          },
          "pass": 25,
          "fail": 1
        }
      ]
    },
    {
      "semesterName": "ZS 2021/2022 - LDF",
      "semesterId": "649",
      "year": 2021,
      "evaluationType": "credit",
      "sourceUrl": "https://is.mendelu.cz/auth/student/hodnoceni.pl?fakulta=38;obdobi=649;predmet=130048;lang=cz",
      "totalPass": 13,
      "totalFail": 1,
      "terms": [
        {
          "term": "Všechny termíny",
          "grades": {
            "zap": 13,
            "nezap": 0,
            "zap-nedost": 1
          },
          "pass": 13,
          "fail": 1
        }
      ]
    }
  ],
  "lastUpdated": "2026-01-12T08:53:23.064446Z"
}