{
  "courseCode": "VA2",
  "aliases": [],
  "stats": [
    {
      "semesterName": "ZS 2020/2021 - PEF",
      "semesterId": "584",
      "year": 2020,
      "type": "exam",
      "sourceUrl": "https://is.mendelu.cz/auth/student/hodnoceni.pl?fakulta=2;obdobi=584;predmet=123777;lang=cz",
      "totalPass": 49,
      "totalFail": 0,
      "terms": [
        {
          "term": "Všechny termíny",
          "grades": {
            "A": 1,
            "B": 3,
            "C": 6,
            "D": 20,
            "E": 19,
            "F": 0,
            "FN": 0
          },
          "pass": 49,
          "fail": 0
        }
      ]
    }
  ],
  "lastUpdated": "2026-01-16T05:55:31.283498Z"
}