{
  "courseCode": "ZPOMI",
  "stats": [
    {
      "semesterName": "ZS 2024/2025 - AF",
      "semesterId": "704",
      "year": 2024,
      "sourceUrl": "https://is.mendelu.cz/auth/student/hodnoceni.pl?fakulta=14;obdobi=704;predmet=152717;lang=cz",
      "totalPass": 25,
      "totalFail": 2,
      "terms": [
        {
          "term": "Všechny termíny",
          "grades": {
            "A": 1,
            "B": 1,
            "C": 8,
            "D": 1,
            "E": 14,
            "F": 1,
            "FN": 1
          },
          "pass": 25,
          "fail": 2
        }
      ]
    },
    {
      "semesterName": "LS 2022/2023 - AF",
      "semesterId": "727",
      "year": 2022,
      "sourceUrl": "https://is.mendelu.cz/auth/student/hodnoceni.pl?fakulta=14;obdobi=727;predmet=141463;lang=cz",
      "totalPass": 43,
      "totalFail": 1,
      "terms": [
        {
          "term": "Všechny termíny",
          "grades": {
            "A": 3,
            "B": 2,
            "C": 11,
            "D": 14,
            "E": 13,
            "F": 1,
            "FN": 0
          },
          "pass": 43,
          "fail": 1
        }
      ]
    },
    {
      "semesterName": "ZS 2023/2024 - AF",
      "semesterId": "733",
      "year": 2023,
      "sourceUrl": "https://is.mendelu.cz/auth/student/hodnoceni.pl?fakulta=14;obdobi=733;predmet=146178;lang=cz",
      "totalPass": 22,
      "totalFail": 2,
      "terms": [
        {
          "term": "Všechny termíny",
          "grades": {
            "A": 1,
            "B": 0,
            "C": 3,
            "D": 7,
            "E": 11,
            "F": 2,
            "FN": 0
          },
          "pass": 22,
          "fail": 2
        }
      ]
    },
    {
      "semesterName": "LS 2023/2024 - AF",
      "semesterId": "752",
      "year": 2023,
      "sourceUrl": "https://is.mendelu.cz/auth/student/hodnoceni.pl?fakulta=14;obdobi=752;predmet=150580;lang=cz",
      "totalPass": 38,
      "totalFail": 0,
      "terms": [
        {
          "term": "Všechny termíny",
          "grades": {
            "A": 3,
            "B": 8,
            "C": 6,
            "D": 9,
            "E": 12,
            "F": 0,
            "FN": 0
          },
          "pass": 38,
          "fail": 0
        }
      ]
    },
    {
      "semesterName": "LS 2024/2025 - AF",
      "semesterId": "779",
      "year": 2024,
      "sourceUrl": "https://is.mendelu.cz/auth/student/hodnoceni.pl?fakulta=14;obdobi=779;predmet=157194;lang=cz",
      "totalPass": 32,
      "totalFail": 1,
      "terms": [
        {
          "term": "Všechny termíny",
          "grades": {
            "A": 4,
            "B": 5,
            "C": 2,
            "D": 7,
            "E": 14,
            "F": 1,
            "FN": 0
          },
          "pass": 32,
          "fail": 1
        }
      ]
    }
  ],
  "lastUpdated": "2025-12-23T12:35:07.706Z"
}